mcp_server_hch/__init__.py
mcp_server_hch/__main__.py
mcp_server_hch/load.py
mcp_server_hch/server.py
mcp_server_hch/docs/hch_knowledge_base_ref.xlsx
mcp_server_hch-0.0.0.dist-info/METADATA
mcp_server_hch-0.0.0.dist-info/WHEEL
mcp_server_hch-0.0.0.dist-info/entry_points.txt
mcp_server_hch-0.0.0.dist-info/RECORD
