Metadata-Version: 2.4
Name: mcp-server-hch
Version: 0.0.0
Summary: MCP server which contains tools for Home Clean Home chatbot service.
Author-email: Zi Min ER <zimin@alvisual.com.sg>
Requires-Python: >=3.11
Requires-Dist: mcp>=1.3.0
Requires-Dist: openpyxl>=3.1.5
Requires-Dist: pandas>=2.2.3
